duo_client/__init__.py
duo_client/accounts.py
duo_client/admin.py
duo_client/auth.py
duo_client/auth_v1.py
duo_client/ca_certs.pem
duo_client/client.py
duo_client/https_wrapper.py
duo_client/util.py
duo_client/logs/__init__.py
duo_client/logs/telephony.py
duo_client-5.4.0.dist-info/LICENSE
duo_client-5.4.0.dist-info/METADATA
duo_client-5.4.0.dist-info/WHEEL
duo_client-5.4.0.dist-info/top_level.txt
duo_client-5.4.0.dist-info/RECORD
