Metadata-Version: 2.2
Name: duo_client
Version: 5.4.0
Summary: Reference client for Duo Security APIs
Home-page: https://github.com/duosecurity/duo_client_python
Author: Duo Security, Inc.
Author-email: support@duosecurity.com
License: BSD
Classifier: Programming Language :: Python
Classifier: License :: OSI Approved :: BSD License
License-File: LICENSE
Requires-Dist: setuptools
Dynamic: author
Dynamic: author-email
Dynamic: classifier
Dynamic: description
Dynamic: description-content-type
Dynamic: home-page
Dynamic: license
Dynamic: requires-dist
Dynamic: summary
